{
    "book": "箴言",
    "chapter": "4",
    "verses": [
        {
            "chapter": "4:1",
            "content": "众子啊，要听父亲的教训，留心得知聪明。",
            "note": ""
        },
        {
            "chapter": "4:2",
            "content": "因我所给你们的是好教训，不可离弃我的法则（注：或作“指教”）。",
            "note": ""
        },
        {
            "chapter": "4:3",
            "content": "我在父亲面前为孝子，在母亲眼中为独一的娇儿。",
            "note": ""
        },
        {
            "chapter": "4:4",
            "content": "父亲教训我说：“你心要存记我的言语，遵守我的命令，便得存活。",
            "note": "作父母最大的责任之一，就是鼓励儿女作智慧人。所罗门告诉我们，当他年幼（娇儿）的时候，他父亲大卫鼓励他寻求智慧（参王上2:1-9；代上28-29章）。他父亲的鼓励，可能促使了所罗门后来向神求智慧（参王上3:9）。智慧是可以藉父母传给儿女，一代一代地传下去的，但追根溯源，所有的智慧皆由神而来，父母劝儿女寻求神，才是让他们获得无穷智慧的惟一方法。假使你的父母从来没有这样教导过你的话，神的道（圣经）也可以像慈爱的父母一样引导你寻找智慧。你可以从圣经之中学到智慧，并在你教导自己儿女的时候，建立传承智慧的传统，使智慧能代代相传。"
        },
        {
            "chapter": "4:5",
            "content": "要得智慧，要得聪明，不可忘记，也不可偏离我口中的言语。",
            "note": ""
        },
        {
            "chapter": "4:6",
            "content": "不可离弃智慧，智慧就护卫你；要爱她，她就保守你。",
            "note": ""
        },
        {
            "chapter": "4:7",
            "content": "智慧为首，所以要得智慧，在你一切所得之内必得聪明（注：或作“用你一切所得的去换聪明”）。",
            "note": "在所罗门年幼时，大卫教导他，寻求神的智慧是所罗门能作的最重要抉择。所罗门听从了父亲的教导，所以当他在位之初、神向他显现并答允赐他一切所求的时候，他只求智慧而不求其他。我们不需要等到神显现时才祈求，现在就可以藉着祷告，大胆地向他求智慧。雅各书1章5节说，神必会应允我们的祈求。"
        },
        {
            "chapter": "4:8",
            "content": "高举智慧，她就使你高升；怀抱智慧，她就使你尊荣。",
            "note": ""
        },
        {
            "chapter": "4:9",
            "content": "她必将华冠加在你头上，把荣冕交给你。”",
            "note": ""
        },
        {
            "chapter": "4:10",
            "content": "我儿，你要听受我的言语，就必延年益寿。",
            "note": ""
        },
        {
            "chapter": "4:11",
            "content": "我已指教你走智慧的道，引导你行正直的路。",
            "note": ""
        },
        {
            "chapter": "4:12",
            "content": "你行走，脚步必不至狭窄；你奔跑，也不至跌倒。",
            "note": ""
        },
        {
            "chapter": "4:13",
            "content": "要持定训诲，不可放松；必当谨守，因为她是你的生命。",
            "note": ""
        },
        {
            "chapter": "4:14",
            "content": "不可行恶人的路，不要走坏人的道。",
            "note": ""
        },
        {
            "chapter": "4:15",
            "content": "要躲避，不可经过，要转身而去。",
            "note": ""
        },
        {
            "chapter": "4:16",
            "content": "这等人若不行恶，不得睡觉；不使人跌倒，睡卧不安。",
            "note": ""
        },
        {
            "chapter": "4:17",
            "content": "因为他们以奸恶吃饼，以强暴喝酒。",
            "note": "朋友也能使你犯罪，人往往很难接受这一点。年轻人都不想自己遭排斥，所以很少反对或批评朋友的错处；许多人甚至看不出朋友的所作所为会产生祸患。我们要接纳别人，但也要正当地质疑别人的行为。在你觉得深受别人影响的时候，应当小心，不要让朋友使你陷入罪中。"
        },
        {
            "chapter": "4:18",
            "content": "但义人的路好像黎明的光，越照越明，直到日午。",
            "note": ""
        },
        {
            "chapter": "4:19",
            "content": "恶人的道好像幽暗，自己不知因什么跌倒。",
            "note": ""
        },
        {
            "chapter": "4:20",
            "content": "我儿，要留心听我的言词，侧耳听我的话语。",
            "note": ""
        },
        {
            "chapter": "4:21",
            "content": "都不可离你的眼目，要存记在你心中。",
            "note": ""
        },
        {
            "chapter": "4:22",
            "content": "因为得着它的，就得了生命，又得了医全体的良药。",
            "note": ""
        },
        {
            "chapter": "4:23",
            "content": "你要保守你心，胜过保守一切（注：或作“你要切切保守你心”），因为一生的果效，是由心发出。",
            "note": ""
        },
        {
            "chapter": "4:24",
            "content": "你要除掉邪僻的口，弃绝乖谬的嘴。",
            "note": ""
        },
        {
            "chapter": "4:25",
            "content": "你的眼目要向前正看，你的眼睛（注：原文作“皮”）当向前直观。",
            "note": ""
        },
        {
            "chapter": "4:26",
            "content": "要修平你脚下的路，坚定你一切的道，",
            "note": ""
        },
        {
            "chapter": "4:27",
            "content": "不可偏向左右，要使你的脚离开邪恶。",
            "note": "我们的心就是指我们对爱与欲望的感受。心主宰我们的生活方式，因为我们总想找时间做自己喜欢的事。所罗门吩咐我们，要保守自己的心，胜过保守一切；一定要专注于那些保守我们行于正道上的意念。要确保你的情感能使你走向正确的方向，不要单单追求所看到的一切。你的眼目要向前正看，专注于目标上，不可分心，更不要走上令你犯罪的歧途。"
        }
    ]
}