{
    "book": "出埃及记",
    "chapter": "35",
    "verses": [
        {
            "chapter": "35:1",
            "content": "摩西招聚以色列全会众，对他们说：“这是耶和华所吩咐的话，叫你们照着行。",
            "note": ""
        },
        {
            "chapter": "35:2",
            "content": "六日要做工，第七日乃为圣日，当向耶和华守为安息圣日；凡这日之内做工的，必把他治死。",
            "note": ""
        },
        {
            "chapter": "35:3",
            "content": "当安息日，不可在你们一切的住处生火。”",
            "note": ""
        },
        {
            "chapter": "35:4",
            "content": "摩西对以色列全会众说：“耶和华所吩咐的是这样：",
            "note": ""
        },
        {
            "chapter": "35:5",
            "content": "你们中间要拿礼物献给耶和华。凡乐意献的，可以拿耶和华的礼物来，就是金、银、铜，",
            "note": ""
        },
        {
            "chapter": "35:6",
            "content": "蓝色、紫色、朱红色线，细麻，山羊毛，",
            "note": ""
        },
        {
            "chapter": "35:7",
            "content": "染红的公羊皮、海狗皮，皂荚木，",
            "note": ""
        },
        {
            "chapter": "35:8",
            "content": "点灯的油，并做膏油和香的香料，",
            "note": ""
        },
        {
            "chapter": "35:9",
            "content": "红玛瑙与别样的宝石，可以镶嵌在以弗得和胸牌上。",
            "note": ""
        },
        {
            "chapter": "35:10",
            "content": "你们中间凡心里有智慧的，都要来做耶和华一切所吩咐的：",
            "note": ""
        },
        {
            "chapter": "35:11",
            "content": "就是帐幕和帐幕的罩棚，并帐幕的盖、钩子、板、闩、柱子、带卯的座；",
            "note": ""
        },
        {
            "chapter": "35:12",
            "content": "柜和柜的杠，施恩座和遮掩柜的幔子；",
            "note": ""
        },
        {
            "chapter": "35:13",
            "content": "桌子和桌子的杠与桌子的一切器具，并陈设饼；",
            "note": ""
        },
        {
            "chapter": "35:14",
            "content": "灯台和灯台的器具，灯盏并点灯的油；",
            "note": ""
        },
        {
            "chapter": "35:15",
            "content": "香坛和坛的杠，膏油和馨香的香料，并帐幕门口的廉子；",
            "note": ""
        },
        {
            "chapter": "35:16",
            "content": "燔祭坛和坛的铜网、坛的杠，并坛的一切器具，洗濯盆和盆座；",
            "note": ""
        },
        {
            "chapter": "35:17",
            "content": "院子的帷子和帷子的柱子，带卯的座和院子的门廉；",
            "note": ""
        },
        {
            "chapter": "35:18",
            "content": "帐幕的橛子，并院子的橛子，和这两处的绳子；",
            "note": ""
        },
        {
            "chapter": "35:19",
            "content": "精工做的礼服，和祭司亚伦并他儿子在圣所用以供祭司职分的圣衣。”",
            "note": "摩西要求有各种技巧的人，奉献才能，同心建造会幕。神赐予每个属他的人特有的才能，我们应当发挥恩赐，就连在人看来与宗教无关的才能，都可用在使神得荣耀的事上。我们可以藉着研究、观摩别人来实习，达到熟能生巧的地步。请你使用才能和技术，帮助你的教会和社区。"
        },
        {
            "chapter": "35:20",
            "content": "以色列全会众从摩西面前退去。",
            "note": ""
        },
        {
            "chapter": "35:21",
            "content": "凡心里受感和甘心乐意的都拿耶和华的礼物来，用以做会幕和其中一切的使用，又用以做圣衣。",
            "note": "凡是心里有感动的人，都乐意将礼物拿来，作建造会幕之用。他们热心来奉献，因为明白奉献对于完成神的居所是何等重要。就跟飞机师与操纵电脑人员在飞机起飞前，能按组检验它的性能是否正常一样，从奉献金钱一事上，神立刻就能看出我们对他的热诚；慷慨的人对神不一定忠心，对他忠心的人则总是慷慨的。"
        },
        {
            "chapter": "35:22",
            "content": "凡心里乐意献礼物的，连男带女，各将金器，就是胸前针、耳环（注：或作“鼻环”）、打印的戒指和手钏，带来献给耶和华。",
            "note": ""
        },
        {
            "chapter": "35:23",
            "content": "凡有蓝色、紫色、朱红色线，细麻，山羊毛，染红的公羊皮、海狗皮的，都拿了来。",
            "note": ""
        },
        {
            "chapter": "35:24",
            "content": "凡献银子和铜给耶和华为礼物的都拿了来。凡有皂荚木可做什么使用的也拿了来。",
            "note": "以色列人曾在埃及作奴隶，又从哪里得到这一切金银财宝的呢？那是在他们出埃及的前夕，从埃及人手中索取后带走的（12:35），其中有金子、银子、珠宝、细麻布、各种牲畜的皮，以及其他贵重物品。"
        },
        {
            "chapter": "35:25",
            "content": "凡心中有智慧的妇女亲手纺线，把所纺的蓝色、紫色、朱红色线和细麻都拿了来。",
            "note": ""
        },
        {
            "chapter": "35:26",
            "content": "凡有智慧心里受感的妇女就纺山羊毛。",
            "note": "懂得纺织的妇女，对建造会幕也贡献良多。巧匠以工作的质量与美观为夸耀，神也关心你的事奉是否精彩；不管你职位高低，都应当在工作上显出他所赐的创造力。"
        },
        {
            "chapter": "35:27",
            "content": "众官长把红玛瑙和别样的宝石，可以镶嵌在以弗得与胸牌上的，都拿了来；",
            "note": ""
        },
        {
            "chapter": "35:28",
            "content": "又拿香料做香，拿油点灯，做膏油。",
            "note": ""
        },
        {
            "chapter": "35:29",
            "content": "以色列人，无论男女，凡甘心乐意献礼物给耶和华的，都将礼物拿来，做耶和华藉摩西所吩咐的一切工。",
            "note": ""
        },
        {
            "chapter": "35:30",
            "content": "摩西对以色列人说：“犹大支派中户珥的孙子、乌利的儿子比撒列，耶和华已经提他的名召他，",
            "note": ""
        },
        {
            "chapter": "35:31",
            "content": "又以　神的灵充满了他，使他有智慧、聪明、知识，能做各样的工；",
            "note": ""
        },
        {
            "chapter": "35:32",
            "content": "能想出巧工，用金、银、铜制造各物；",
            "note": ""
        },
        {
            "chapter": "35:33",
            "content": "又能刻宝石，可以镶嵌；能雕刻木头，能做各样的巧工。",
            "note": ""
        },
        {
            "chapter": "35:34",
            "content": "耶和华又使他和但支派中亚希撒抹的儿子亚何利亚伯，心里灵明，能教导人。",
            "note": ""
        },
        {
            "chapter": "35:35",
            "content": "耶和华使他们的心满有智慧，能做各样的工。无论是雕刻的工，巧匠的工，用蓝色、紫色、朱红色线和细麻绣花的工，并机匠的工，他们都能做，也能想出奇巧的工。”",
            "note": ""
        }
    ]
}