{
    "book": "历代志上",
    "chapter": "25",
    "verses": [
        {
            "chapter": "25:1",
            "content": "大卫和众首领分派亚萨、希幔并耶杜顿的子孙弹琴、鼓瑟、敲钹、唱歌（注：原文作“说预言”。本章同）。他们供职的人数记在下面：",
            "note": "说预言不但讲述未来的事，也包括唱诗颂赞神与传扬他的信息（参林前14章）。作先知的可能是乐师、农夫（参摩1:1）、主妇（参王下22:14）或领袖（参申34:10）──凡是勇敢、准确地代神传言，想领人民回转敬拜他的人，都可以作先知。大卫从许多歌唱者与乐师之中，选出这一班才华出众的人来向别人传颂神，并以音乐鼓舞人心。"
        },
        {
            "chapter": "25:2",
            "content": "亚萨的儿子撒刻、约瑟、尼探雅、亚萨利拉都归亚萨指教，遵王的旨意唱歌。",
            "note": ""
        },
        {
            "chapter": "25:3",
            "content": "耶杜顿的儿子基大利、西利、耶筛亚、哈沙比雅、玛他提雅、示每，共六人，都归他们父亲耶杜顿指教，弹琴、唱歌、称谢颂赞耶和华。",
            "note": ""
        },
        {
            "chapter": "25:4",
            "content": "希幔的儿子布基雅、玛探雅、乌薛、细布业、耶利摩、哈拿尼雅、哈拿尼、以利亚他、基大利提、罗幔提以谢、约施比加沙、玛罗提、何提、玛哈秀，",
            "note": ""
        },
        {
            "chapter": "25:5",
            "content": "这都是希幔的儿子，吹角颂赞。希幔奉　神之命作王的先见。　神赐给希幔十四个儿子、三个女儿，",
            "note": ""
        },
        {
            "chapter": "25:6",
            "content": "都归他们父亲指教，在耶和华的殿唱歌、敲钹、弹琴、鼓瑟，办　神殿的事务。亚萨、耶杜顿、希幔都是王所命定的。",
            "note": ""
        },
        {
            "chapter": "25:7",
            "content": "他们和他们的弟兄学习颂赞耶和华，善于歌唱的，共有二百八十八人。",
            "note": "在帐幕之中有许多方式可以敬拜神。有些人说预言和唱歌（25:1），有人称谢颂赞神（25:3），也有人吹奏乐器（25:6-7），神要全体的子民都敬拜他。你可能不是音乐家，不是先知教师，但是凡你所献上的一切，神都会悦纳。你要发展自己的特殊才华来事奉神（参罗12:3-8；林前12:29-31）。"
        },
        {
            "chapter": "25:8",
            "content": "这些人无论大小，为师的为徒的，都一同掣签分了班次。",
            "note": ""
        },
        {
            "chapter": "25:9",
            "content": "掣签的时候，第一掣出来的是亚萨的儿子约瑟。第二是基大利，他和他弟兄并儿子共十二人。",
            "note": ""
        },
        {
            "chapter": "25:10",
            "content": "第三是撒刻，他和他儿子并弟兄共十二人。",
            "note": ""
        },
        {
            "chapter": "25:11",
            "content": "第四是伊洗利，他和他儿子并弟兄共十二人。",
            "note": ""
        },
        {
            "chapter": "25:12",
            "content": "第五是尼探雅，他和他儿子并弟兄共十二人。",
            "note": ""
        },
        {
            "chapter": "25:13",
            "content": "第六是布基雅，他和他儿子并弟兄共十二人。",
            "note": ""
        },
        {
            "chapter": "25:14",
            "content": "第七是耶萨利拉，他和他儿子并弟兄共十二人。",
            "note": ""
        },
        {
            "chapter": "25:15",
            "content": "第八是耶筛亚，他和他儿子并弟兄共十二人。",
            "note": ""
        },
        {
            "chapter": "25:16",
            "content": "第九是玛探雅，他和他儿子并弟兄共十二人。",
            "note": ""
        },
        {
            "chapter": "25:17",
            "content": "第十是示每，他和他儿子并弟兄共十二人。",
            "note": ""
        },
        {
            "chapter": "25:18",
            "content": "第十一是亚萨烈，他和他儿子并弟兄共十二人。",
            "note": ""
        },
        {
            "chapter": "25:19",
            "content": "第十二是哈沙比雅，他和他儿子并弟兄共十二人。",
            "note": ""
        },
        {
            "chapter": "25:20",
            "content": "第十三是书巴业，他和他儿子并弟兄共十二人。",
            "note": ""
        },
        {
            "chapter": "25:21",
            "content": "第十四是玛他提雅，他和他儿子并弟兄共十二人。",
            "note": ""
        },
        {
            "chapter": "25:22",
            "content": "第十五是耶利摩，他和他儿子并弟兄共十二人。",
            "note": ""
        },
        {
            "chapter": "25:23",
            "content": "第十六是哈拿尼雅，他和他儿子并弟兄共十二人。",
            "note": ""
        },
        {
            "chapter": "25:24",
            "content": "第十七是约施比加沙，他和他儿子并弟兄共十二人。",
            "note": ""
        },
        {
            "chapter": "25:25",
            "content": "第十八是哈拿尼，他和他儿子并弟兄共十二人。",
            "note": ""
        },
        {
            "chapter": "25:26",
            "content": "第十九是玛罗提，他和他儿子并弟兄共十二人。",
            "note": ""
        },
        {
            "chapter": "25:27",
            "content": "第二十是以利亚他，他和他儿子并弟兄共十二人。",
            "note": ""
        },
        {
            "chapter": "25:28",
            "content": "第二十一是何提，他和他儿子并弟兄共十二人。",
            "note": ""
        },
        {
            "chapter": "25:29",
            "content": "第二十二是基大利提，他和他儿子并弟兄共十二人。",
            "note": ""
        },
        {
            "chapter": "25:30",
            "content": "第二十三是玛哈秀，他和他儿子并弟兄共十二人。",
            "note": ""
        },
        {
            "chapter": "25:31",
            "content": "第二十四是罗幔提以谢，他和他儿子并弟兄共十二人。",
            "note": "大卫将歌者、乐手分为二十四班，与祭司的二十四班相配合（24:7-15）。这种任职的班次，使圣殿的管理有条不紊，训练人员卓有功效，并令敬拜神的方式多采多姿。因为每一班都任职一个短期，就能让更多人有参与的机会。"
        }
    ]
}