{
    "book": "以西结书",
    "chapter": "2",
    "verses": [
        {
            "chapter": "2:1",
            "content": "他对我说：“人子啊，你站起来，我要和你说话。”",
            "note": "永生之神对以西结说话的时候，称呼他为“人子”。这是在强调以西结与神之间的距离。令人希奇的是，神选用了地上有限、不完全的人来执行神的旨意。神是用地上的尘土造的我们，将生命气息吹进我们的里面，并要我们来服事他。"
        },
        {
            "chapter": "2:2",
            "content": "他对我说话的时候，灵就进入我里面，使我站起来，我便听见那位对我说话的声音。",
            "note": "我们只能想像以西结所看到的异象是个什么样子。以西结对自己所看到的肯定也有许多不明白的地方，但他知道每一部分都来自于神，所以非常重要。神看到以西结坦白和顺服的态度，就将自己的灵充满了他，并给了他去完成工作的能力。神并不指望我们弄懂神的一切，而是要我们作服从的仆人，并忠实于所知道的真实正确的道理。"
        },
        {
            "chapter": "2:3",
            "content": "他对我说：“人子啊，我差你往悖逆的国民以色列人那里去。他们是悖逆我的，他们和他们的列祖违背我，直到今日。",
            "note": ""
        },
        {
            "chapter": "2:4",
            "content": "这众子面无羞耻，心里刚硬。我差你往他们那里去，你要对他们说：‘主耶和华如此说。’",
            "note": ""
        },
        {
            "chapter": "2:5",
            "content": "他们或听或不听（他们是悖逆之家），必知道在他们中间有了先知。",
            "note": "神说百姓“顽梗悖逆”是因为他们拒绝认罪。悖逆是当时以色列民族的特点。即使在神指出他们的错误行为后，他们仍对真理置若罔闻。神是不是也指出我们身上的某些罪呢？我们不要顽固，要向神认罪，并开始为神而活。我们现在顺服神，就是为最后的审判作好准备（参太25:31-46）。"
        },
        {
            "chapter": "2:6",
            "content": "人子啊，虽有荆棘和蒺藜在你那里，你又住在蝎子中间，总不要怕他们，也不要怕他们的话；他们虽是悖逆之家，还不要怕他们的话，也不要因他们的脸色惊惶。",
            "note": ""
        },
        {
            "chapter": "2:7",
            "content": "他们或听或不听，你只管将我的话告诉他们。他们是极其悖逆的。",
            "note": ""
        },
        {
            "chapter": "2:8",
            "content": "人子啊，要听我对你所说的话，不要悖逆像那悖逆之家，你要开口吃我所赐给你的。”",
            "note": "神给了以西结一项艰巨的任务。神要他向那些不懂得感恩，满腹牢骚的人传讲神的信息。有时候我们必须给不友善的人作榜样，或者分享我们的信仰。主告诉以西结不要害怕也不要反抗，不用管人们听不听，只管将神的话告诉他们。神也要我们无论得时不得时，总要去传福音（参提后4:2）。"
        },
        {
            "chapter": "2:9",
            "content": "我观看，见有一只手向我伸出来，手中有一书卷。",
            "note": ""
        },
        {
            "chapter": "2:10",
            "content": "他将书卷在我面前展开，内外都写着字，其上所写的有哀号、叹息、悲痛的话。",
            "note": "古书经常以卷而论，一页约9公尺长，能两边同时卷起来。通常只是在书卷的一面上书写，可是这一次的警告文已写到另一面去了。这足以说明要降临到犹大的审判的厉害程度。"
        }
    ]
}